swarmauri_vectorstore_redis/RedisDocumentRetriever.py
swarmauri_vectorstore_redis/RedisVectorStore.py
swarmauri_vectorstore_redis/__init__.py
swarmauri_vectorstore_redis-0.7.5.dist-info/LICENSE
swarmauri_vectorstore_redis-0.7.5.dist-info/METADATA
swarmauri_vectorstore_redis-0.7.5.dist-info/WHEEL
swarmauri_vectorstore_redis-0.7.5.dist-info/entry_points.txt
swarmauri_vectorstore_redis-0.7.5.dist-info/RECORD
