Metadata-Version: 2.3
Name: swarmauri_vectorstore_redis
Version: 0.7.5
Summary: Swarmauri Redis Vector Store
License: Apache-2.0
Author: Jacob Stewart
Author-email: jacob@swarmauri.com
Requires-Python: >=3.10,<3.13
Classifier: License :: OSI Approved :: Apache Software License
Classifier: Programming Language :: Python :: 3.10
Classifier: Programming Language :: Python :: 3.11
Classifier: Programming Language :: Python :: 3.12
Requires-Dist: redis (>=4.0)
Requires-Dist: redisearch
Requires-Dist: swarmauri_base
Requires-Dist: swarmauri_core
Requires-Dist: swarmauri_embedding_doc2vec
Requires-Dist: swarmauri_standard
